wredis/__init__.py
wredis/bitmap/__init__.py
wredis/bitmap/bitmap.py
wredis/hash/__init__.py
wredis/hash/hash.py
wredis/pubsub/__init__.py
wredis/pubsub/pupsub.py
wredis/queue/__init__.py
wredis/queue/queue.py
wredis/sets/__init__.py
wredis/sets/sets.py
wredis/sortedset/__init__.py
wredis/sortedset/sortedset.py
wredis/streams/__init__.py
wredis/streams/streams.py
wredis-0.1.0.dist-info/LICENSE
wredis-0.1.0.dist-info/METADATA
wredis-0.1.0.dist-info/WHEEL
wredis-0.1.0.dist-info/top_level.txt
wredis-0.1.0.dist-info/RECORD
