Metadata-Version: 2.2
Name: wredis
Version: 0.1.0
Summary: Redis control with Python
Home-page: https://github.com/wisrovi/wredis
Author: William Steve Rodriguez Villamizar
Author-email: wisrovi <wisrovi.rodriguez@gmail.com>
License: MIT License
Project-URL: Homepage, https://github.com/wisrovi/wredis
Project-URL: Bug Tracker, https://github.com/wisrovi/wredis/issues
Classifier: Programming Language :: Python :: 3
Classifier: License :: OSI Approved :: MIT License
Classifier: Operating System :: OS Independent
Requires-Python: >=3.6, <3.12
License-File: LICENSE
Dynamic: author
Dynamic: home-page
Dynamic: requires-python
